jnius_config.py
setup_sdist.py
jnius/__init__.py
jnius/env.py
jnius/jnius.cp314t-win_amd64.pyd
jnius/reflect.py
jnius/signatures.py
jnius/src/org/jnius/NativeInvocationHandler.class
jnius/src/org/jnius/NativeInvocationHandler.java
pyjnius-1.7.0.dist-info/licenses/LICENSE
pyjnius-1.7.0.dist-info/METADATA
pyjnius-1.7.0.dist-info/WHEEL
pyjnius-1.7.0.dist-info/top_level.txt
pyjnius-1.7.0.dist-info/RECORD
