Metadata-Version: 2.1
Name: pyjnius
Version: 1.7.0
Summary: A Python library for accessing access Java classes as using the Java Native Interface (JNI).
Home-page: https://github.com/kivy/pyjnius
Author: Kivy Team and other contributors
Author-email: kivy-dev@googlegroups.com
Project-URL: Website, https://kivy.org
Project-URL: Documentation, https://pyjnius.readthedocs.io
Project-URL: Source, https://github.com/kivy/pyjnius
Project-URL: Bug Reports, https://github.com/kivy/pyjnius/issues
Keywords: Java JNI Android
Classifier: Development Status :: 5 - Production/Stable
Classifier: Intended Audience :: Developers
Classifier: License :: OSI Approved :: MIT License
Classifier: Natural Language :: English
Classifier: Operating System :: MacOS
Classifier: Operating System :: Microsoft :: Windows
Classifier: Operating System :: POSIX :: Linux
Classifier: Operating System :: Android
Classifier: Programming Language :: Python :: 3.9
Classifier: Programming Language :: Python :: 3.10
Classifier: Programming Language :: Python :: 3.11
Classifier: Programming Language :: Python :: 3.12
Classifier: Programming Language :: Python :: 3.13
Classifier: Topic :: Software Development :: Libraries :: Application Frameworks
License-File: LICENSE
Provides-Extra: ci
Requires-Dist: coveralls; extra == "ci"
Requires-Dist: pytest-rerunfailures; extra == "ci"
Provides-Extra: dev
Requires-Dist: pytest; extra == "dev"
Requires-Dist: pytest-cov; extra == "dev"
Requires-Dist: pycodestyle; extra == "dev"
